heroku_config_vars_formatter/__init__.py
heroku_config_vars_formatter/formatting.py
heroku_config_vars_formatter/main.py
heroku_config_vars_formatter-1.0.1.dist-info/entry_points.txt
heroku_config_vars_formatter-1.0.1.dist-info/WHEEL
heroku_config_vars_formatter-1.0.1.dist-info/METADATA
heroku_config_vars_formatter-1.0.1.dist-info/RECORD
