Metadata-Version: 2.1
Name: heroku-config-vars-formatter
Version: 1.0.1
Summary: A small utility to set Heroku config vars in a shell.
Author: Martin Winkel
Author-email: martin@pythomation.de
Requires-Python: >=3.6
Classifier: Programming Language :: Python :: 3
Classifier: Programming Language :: Python :: 3.10
Classifier: Programming Language :: Python :: 3.6
Classifier: Programming Language :: Python :: 3.7
Classifier: Programming Language :: Python :: 3.8
Classifier: Programming Language :: Python :: 3.9
Requires-Dist: pyperclip (>=1.8.2,<2.0.0)
